pdm_tester-0.1.1.dist-info/METADATA
pdm_tester-0.1.1.dist-info/WHEEL
pdm_tester/__init__.py
pdm_tester-0.1.1.dist-info/RECORD
